{
  "Todos": [
    {
      "text": "CRUD",
      "checked": false,
      "id": 1
    },
    {
      "text": "json-server",
      "checked": false,
      "id": 2
    },
    {
      "text": "figma",
      "checked": false,
      "id": 3
    },
    {
      "text": "1",
      "checked": false,
      "id": 4
    },
    {
      "text": "2",
      "checked": false,
      "id": 5
    },
    {
      "text": "3",
      "checked": false,
      "id": 6
    },
    {
      "text": "4",
      "checked": false,
      "id": 7
    },
    {
      "text": "5",
      "checked": false,
      "id": 8
    },
    {
      "text": "6",
      "checked": false,
      "id": 9
    },
    {
      "text": "7",
      "checked": false,
      "id": 10
    },
    {
      "text": "8",
      "checked": false,
      "id": 11
    },
    {
      "text": "9",
      "checked": false,
      "id": 12
    },
    {
      "text": "10",
      "checked": false,
      "id": 13
    }
  ]
}